<?xml version="1.0"?>
<SL_StatusEffect xmlns:xsd="http://www.w3.org/2001/XMLSchema" xmlns:xsi="http://www.w3.org/2001/XMLSchema-instance">
  <TargetStatusIdentifier>Doom</TargetStatusIdentifier>
  <NewStatusID>30</NewStatusID>
  <StatusIdentifier>StartTag</StatusIdentifier>
  <Name>Fullstop</Name>
  <Description>Unable to act.</Description>
  <Lifespan>-1</Lifespan>
  <RefreshRate>0.5</RefreshRate>
  <Purgeable>true</Purgeable>
  <Priority>1</Priority>
  <IgnoreBarrier>false</IgnoreBarrier>
  <BuildupRecoverySpeed>3</BuildupRecoverySpeed>
  <IgnoreBuildupIfApplied>false</IgnoreBuildupIfApplied>
  <AmplifiedStatusIdentifier />
  <RemoveRequiredStatus>false</RemoveRequiredStatus>
  <NormalizeDamageDisplay>false</NormalizeDamageDisplay>
  <DisplayedInHUD>false</DisplayedInHUD>
  <IsHidden>true</IsHidden>
  <IsMalusEffect>false</IsMalusEffect>
  <DelayedDestroyTime>0</DelayedDestroyTime>
  <ActionOnHit>None</ActionOnHit>
  <FamilyMode>Reference</FamilyMode>
  <BindFamily>
    <UID>com.iggy.starttagfam</UID>
    <Name>StartTagFam</Name>
    <StackBehaviour>IndependantUnique</StackBehaviour>
    <MaxStackCount>-1</MaxStackCount>
    <LengthType>Short</LengthType>
  </BindFamily>
  <PlayFXOnActivation>true</PlayFXOnActivation>
  <FXOffset>
    <x>0</x>
    <y>0</y>
    <z>0</z>
  </FXOffset>
  <VFXInstantiationType>VFX</VFXInstantiationType>
  <VFXPrefab>HexDoomVFX</VFXPrefab>
  <SpecialSFX>NONE</SpecialSFX>
  <PlaySpecialFXOnStop>false</PlaySpecialFXOnStop>
  <EffectBehaviour>Destroy</EffectBehaviour>
  <Effects>

  </Effects>
</SL_StatusEffect>